Metadata-Version: 2.1
Name: anil-probdist
Version: 0.1
Summary: Gaussian distributions
